{
  "snapshotId": "clubelo-2026-05-16-052df7836ec39f46",
  "schemaVersion": 1,
  "source": "clubelo",
  "observedAt": "2026-07-23T08:53:54.246Z",
  "effectiveAt": "2026-05-16",
  "contentHash": "052df7836ec39f46",
  "correctionOf": null,
  "note": "backfilled from clubelo published history — retrospective use only",
  "ratings": {
    "Augsburg": 1654.68005371,
    "Bayern": 2001.6706543,
    "Bremen": 1613.83959961,
    "Dortmund": 1831.23669434,
    "Frankfurt": 1664.49060059,
    "Freiburg": 1719.99169922,
    "Gladbach": 1625.19494629,
    "Heidenheim": 1564.32189941,
    "Hoffenheim": 1720.29016113,
    "HSV": 1597.82080078,
    "Köln": 1571.65649414,
    "Leipzig": 1778.13549805,
    "Leverkusen": 1812.64074707,
    "Mainz": 1664.46154785,
    "St. Pauli": 1546.94628906,
    "Stuttgart": 1767.41186523,
    "Union Berlin": 1605.48498535,
    "Wolfsburg": 1589.85327148,
    "Bielefeld": 1386.71911621,
    "Bochum": 1480.27392578,
    "Braunschweig": 1386.95715332,
    "Darmstadt": 1477.32385254,
    "Dresden": 1408.26538086,
    "Düsseldorf": 1425.73278809,
    "Elversberg": 1525.5423584,
    "Fürth": 1383.61218262,
    "Hannover": 1533.60070801,
    "Hertha": 1484.00610352,
    "Kaiserslautern": 1448.92565918,
    "Karlsruhe": 1446.4362793,
    "Kiel": 1473.01843262,
    "Magdeburg": 1451.1463623,
    "Münster": 1354.92175293,
    "Nürnberg": 1457.26867676,
    "Paderborn": 1515.68908691,
    "Schalke": 1518.12182617
  }
}
