{
  "snapshotId": "clubelo-2025-11-08-d70705120b0f434e",
  "schemaVersion": 1,
  "source": "clubelo",
  "observedAt": "2026-07-23T08:53:54.246Z",
  "effectiveAt": "2025-11-08",
  "contentHash": "d70705120b0f434e",
  "correctionOf": null,
  "note": "backfilled from clubelo published history — retrospective use only",
  "ratings": {
    "Augsburg": 1613.32836914,
    "Bayern": 2000.3338623,
    "Bremen": 1698.30822754,
    "Dortmund": 1857.87646484,
    "Frankfurt": 1756.55712891,
    "Freiburg": 1712.07141113,
    "Gladbach": 1629.30310059,
    "Heidenheim": 1555.60339355,
    "Hoffenheim": 1660.50524902,
    "HSV": 1569.11315918,
    "Köln": 1610.19396973,
    "Leipzig": 1781.31896973,
    "Leverkusen": 1847.30908203,
    "Mainz": 1688.15307617,
    "St. Pauli": 1568.07446289,
    "Stuttgart": 1733.25219727,
    "Union Berlin": 1635.51452637,
    "Wolfsburg": 1628.60571289,
    "Bielefeld": 1392.72119141,
    "Bochum": 1509.34997559,
    "Braunschweig": 1368.14318848,
    "Darmstadt": 1487.54504395,
    "Dresden": 1342.3425293,
    "Düsseldorf": 1467.2512207,
    "Elversberg": 1543.46459961,
    "Fürth": 1398.88146973,
    "Hannover": 1503.89355469,
    "Hertha": 1488.05493164,
    "Kaiserslautern": 1496.41418457,
    "Karlsruhe": 1517.15039062,
    "Kiel": 1521.28808594,
    "Magdeburg": 1416.27429199,
    "Münster": 1413.80151367,
    "Nürnberg": 1444.78051758,
    "Paderborn": 1548.3729248,
    "Schalke": 1480.89453125
  }
}
